{
  "generatedAt": "2026-07-17T20:45:09.960Z",
  "totals": {
    "totalFiles": 501,
    "tsFiles": 262,
    "jsFiles": 239,
    "tsWrappers": 0,
    "jsWrappers": 0,
    "jsImportsExplicit": 73,
    "jsImportTargetsExplicit": [
      [
        "./ExecuteCapabilityUseCase.test.js",
        1
      ],
      [
        "./RegisterCapabilityUseCase.test.js",
        1
      ],
      [
        "./CapabilityRegistry.test.js",
        1
      ],
      [
        "./ErrorClassifier.test.js",
        1
      ],
      [
        "./PermissionChecker.test.js",
        1
      ],
      [
        "./RetryPolicy.test.js",
        1
      ],
      [
        "./TimeoutPolicy.test.js",
        1
      ],
      [
        "./EventBus.test.js",
        1
      ],
      [
        "./EventPublisher.test.js",
        1
      ],
      [
        "./TenantContext.test.js",
        1
      ],
      [
        "./TenantGuard.test.js",
        1
      ],
      [
        "./api.e2e.test.js",
        1
      ],
      [
        "./database.e2e.test.js",
        1
      ],
      [
        "./RuntimeEngine.contract.test.js",
        1
      ],
      [
        "./RuntimeEngine.integration.test.js",
        1
      ],
      [
        "./RuntimeEngine.test.js",
        1
      ],
      [
        "./ExecutionContext.test.js",
        1
      ],
      [
        "./ExecutionLifecycle.test.js",
        1
      ],
      [
        "./EventDispatcher.test.js",
        1
      ],
      [
        "./GenerarRespuestaUseCase.test.js",
        1
      ],
      [
        "./AgregarMensajeAlBufferUseCase.test.js",
        1
      ],
      [
        "./CerrarProcesarBufferUseCase.test.js",
        1
      ],
      [
        "./BufferExpirationWorker.test.js",
        1
      ],
      [
        "./MessageBuffer.test.js",
        1
      ],
      [
        "./ConversationFlow.test.js",
        1
      ],
      [
        "./ExpressApp.test.js",
        1
      ],
      [
        "./ConversationControlController.test.js",
        1
      ],
      [
        "./DashboardController.test.js",
        1
      ],
      [
        "./EmpresaController.test.js",
        1
      ],
      [
        "./UsuarioController.test.js",
        1
      ],
      [
        "./auth.test.js",
        1
      ],
      [
        "./rateLimit.test.js",
        1
      ],
      [
        "./UseCases.test.js",
        1
      ],
      [
        "./ValueObjects.test.js",
        1
      ],
      [
        "./PrismaDashboardRepository.test.js",
        1
      ],
      [
        "./ActivarEmpresaUseCase.test.js",
        1
      ],
      [
        "./ActualizarEmpresaUseCase.test.js",
        1
      ],
      [
        "./CancelarEmpresaUseCase.test.js",
        1
      ],
      [
        "./CrearEmpresaUseCase.test.js",
        1
      ],
      [
        "./SuspenderEmpresaUseCase.test.js",
        1
      ],
      [
        "./Empresa.test.js",
        1
      ],
      [
        "./EmpresaRepository.test.js",
        1
      ],
      [
        "./FakeEmpresaRepository.test.js",
        1
      ],
      [
        "./PrismaEmpresaRepository.test.js",
        1
      ],
      [
        "./BloquearCerrarConversacionUseCase.test.js",
        1
      ],
      [
        "./CrearConversationSessionUseCase.test.js",
        1
      ],
      [
        "./DetectarIntervencionHumanaUseCase.test.js",
        1
      ],
      [
        "./EvaluarReanudacionBotUseCase.test.js",
        1
      ],
      [
        "./BotResumptionWorker.test.js",
        1
      ],
      [
        "./ConversationSession.test.js",
        1
      ],
      [
        "./ConversationState.test.js",
        1
      ],
      [
        "./EvolutionWebhookAdapter.test.js",
        1
      ],
      [
        "./EvolutionWebhookHandler.test.js",
        1
      ],
      [
        "./FakeConversationSessionRepository.test.js",
        1
      ],
      [
        "./PrismaConversationSessionRepository.test.js",
        1
      ],
      [
        "./ActivarUsuarioUseCase.test.js",
        1
      ],
      [
        "./ActualizarUsuarioUseCase.test.js",
        1
      ],
      [
        "./CancelarUsuarioUseCase.test.js",
        1
      ],
      [
        "./CrearUsuarioUseCase.test.js",
        1
      ],
      [
        "./SuspenderUsuarioUseCase.test.js",
        1
      ],
      [
        "./Usuario.test.js",
        1
      ],
      [
        "./FakeUsuarioRepository.test.js",
        1
      ],
      [
        "./PrismaUsuarioRepository.integration.test.js",
        1
      ],
      [
        "./PrismaUsuarioRepository.test.js",
        1
      ],
      [
        "./EnviarMensajeUseCase.test.js",
        1
      ],
      [
        "./env.test.js",
        1
      ],
      [
        "./prisma.test.js",
        1
      ],
      [
        "./DomainError.test.js",
        1
      ],
      [
        "./NotFoundError.test.js",
        1
      ],
      [
        "./ValidationError.test.js",
        1
      ],
      [
        "./EventSubscriber.test.js",
        1
      ],
      [
        "./logger.test.js",
        1
      ],
      [
        "./UuidGenerator.test.js",
        1
      ]
    ],
    "jsImportTargetsResolved": [
      [
        "src/shared/errors/NotFoundError.js",
        36
      ],
      [
        "src/shared/errors/ValidationError.js",
        33
      ],
      [
        "src/core/kernel/events/DomainEvent.js",
        32
      ],
      [
        "src/core/security/TenantError.js",
        15
      ],
      [
        "src/core/security/TenantGuard.js",
        15
      ],
      [
        "src/shared/errors/DomainError.js",
        15
      ],
      [
        "src/shared/database/prisma.js",
        12
      ],
      [
        "src/shared/tenant/TenantGuard.js",
        12
      ],
      [
        "src/modules/human-intervention/domain/entities/ConversationSession.js",
        12
      ],
      [
        "src/engines/conversation-engine/buffer/domain/entities/MessageBuffer.js",
        11
      ],
      [
        "src/modules/empresa/domain/entities/Empresa.js",
        11
      ],
      [
        "src/modules/usuario/domain/entities/Usuario.js",
        11
      ],
      [
        "src/core/kernel/events/EventBus.js",
        8
      ],
      [
        "src/shared/events/EventBus.js",
        7
      ],
      [
        "src/engines/conversation-engine/state-machine/domain/entities/ConversationFlow.js",
        7
      ],
      [
        "src/infrastructure/api/contracts/index.js",
        7
      ],
      [
        "src/core/capability/domain/CapabilityRegistry.js",
        6
      ],
      [
        "src/core/capability/domain/Capability.js",
        6
      ],
      [
        "src/shared/logger/Logger.js",
        6
      ],
      [
        "src/engines/conversation-engine/buffer/domain/events/BufferListo.js",
        6
      ],
      [
        "src/engines/conversation-engine/buffer/domain/repositories/MessageBufferRepository.js",
        6
      ],
      [
        "src/infrastructure/api/interfaces/middleware/auth.js",
        6
      ],
      [
        "src/core/execution-policy/domain/ErrorClassifier.js",
        5
      ],
      [
        "src/core/execution-policy/domain/PermissionChecker.js",
        5
      ],
      [
        "src/engines/conversation-engine/state-machine/domain/repositories/ConversationFlowRepository.js",
        5
      ],
      [
        "src/infrastructure/api/contracts/Metadata.js",
        5
      ],
      [
        "src/infrastructure/api/errors/ApiHttpException.js",
        5
      ],
      [
        "src/core/contracts/ExecutionContext.ts",
        4
      ],
      [
        "src/core/security/TenantContext.js",
        4
      ],
      [
        "src/engines/agent-runtime/application/RuntimeEngine.js",
        4
      ],
      [
        "src/infrastructure/api/interfaces/controllers/DashboardController.js",
        4
      ],
      [
        "src/core/capability/infrastructure/InMemoryCapabilityRepository.js",
        3
      ],
      [
        "src/core/execution-policy/domain/RetryPolicy.js",
        3
      ],
      [
        "src/core/execution-policy/domain/TimeoutPolicy.js",
        3
      ],
      [
        "src/engines/agent-runtime/infrastructure/EventDispatcher.js",
        3
      ],
      [
        "src/engines/agent-runtime/domain/ExecutionContext.js",
        3
      ],
      [
        "src/engines/agent-runtime/domain/ExecutionLifecycle.js",
        3
      ],
      [
        "src/engines/ai-engine/domain/entities/AIRequest.js",
        3
      ],
      [
        "src/engines/ai-engine/domain/events/RespuestaGenerada.js",
        3
      ],
      [
        "src/engines/ai-engine/domain/events/GeneracionFallida.js",
        3
      ],
      [
        "src/engines/conversation-engine/buffer/domain/events/BufferAbierto.js",
        3
      ],
      [
        "src/engines/conversation-engine/buffer/infrastructure/persistence/FakeMessageBufferRepository.js",
        3
      ],
      [
        "src/engines/conversation-engine/buffer/application/use-cases/CerrarBufferUseCase.js",
        3
      ],
      [
        "src/engines/conversation-engine/buffer/domain/events/BufferProcesado.js",
        3
      ],
      [
        "src/engines/conversation-engine/state-machine/domain/events/EtapaAvanzada.js",
        3
      ],
      [
        "src/engines/conversation-engine/state-machine/domain/events/FlujoFinalizado.js",
        3
      ],
      [
        "src/engines/conversation-engine/state-machine/domain/events/FlujoIniciado.js",
        3
      ],
      [
        "src/infrastructure/api/interfaces/controllers/EmpresaController.js",
        3
      ],
      [
        "src/infrastructure/api/interfaces/controllers/UsuarioController.js",
        3
      ],
      [
        "src/infrastructure/api/interfaces/controllers/ConversationControlController.js",
        3
      ],
      [
        "src/infrastructure/api/interfaces/routes/dashboardRoutes.js",
        3
      ],
      [
        "src/infrastructure/api/interfaces/middleware/rateLimit.js",
        3
      ],
      [
        "src/infrastructure/api/infrastructure/ExpressApp.js",
        3
      ],
      [
        "src/modules/dashboard/infrastructure/persistence/PrismaDashboardRepository.js",
        3
      ],
      [
        "src/modules/dashboard/application/use-cases/ObtenerMetricasGlobales.js",
        3
      ],
      [
        "src/modules/dashboard/application/use-cases/ObtenerActividadReciente.js",
        3
      ],
      [
        "src/modules/dashboard/domain/entities/DashboardMetrics.js",
        3
      ],
      [
        "src/infrastructure/api/validators/commonValidators.js",
        3
      ],
      [
        "src/modules/empresa/domain/repositories/EmpresaRepository.js",
        3
      ],
      [
        "src/modules/human-intervention/infrastructure/persistence/FakeConversationSessionRepository.js",
        3
      ],
      [
        "src/core/capability/application/RegisterCapabilityUseCase.js",
        2
      ],
      [
        "src/core/kernel/events/EventPublisher.js",
        2
      ],
      [
        "src/engines/ai-engine/application/use-cases/GenerarRespuestaUseCase.js",
        2
      ],
      [
        "src/engines/conversation-engine/buffer/domain/valueObjects/BufferState.js",
        2
      ],
      [
        "src/engines/conversation-engine/state-machine/domain/valueObjects/FlowStage.js",
        2
      ],
      [
        "src/infrastructure/api/contracts/ProblemDetails.js",
        2
      ],
      [
        "src/infrastructure/api/contracts/Cursor.js",
        2
      ],
      [
        "src/infrastructure/api/contracts/Pagination.js",
        2
      ],
      [
        "src/infrastructure/api/contracts/ApiResponse.js",
        2
      ],
      [
        "src/infrastructure/api/contracts/ApiError.js",
        2
      ],
      [
        "src/infrastructure/api/interfaces/routes/empresasRoutes.js",
        2
      ],
      [
        "src/infrastructure/api/interfaces/routes/usuariosRoutes.js",
        2
      ],
      [
        "src/infrastructure/api/interfaces/routes/conversacionesRoutes.js",
        2
      ],
      [
        "src/modules/dashboard/domain/valueObjects/MetricasEmpresa.js",
        2
      ],
      [
        "src/modules/dashboard/domain/valueObjects/MetricasUsuario.js",
        2
      ],
      [
        "src/modules/dashboard/domain/valueObjects/MetricasConversacion.js",
        2
      ],
      [
        "src/modules/empresa/domain/events/EmpresaActivada.js",
        2
      ],
      [
        "src/modules/empresa/domain/events/EmpresaActualizada.js",
        2
      ],
      [
        "src/modules/empresa/domain/events/EmpresaCancelada.js",
        2
      ],
      [
        "src/modules/empresa/domain/events/EmpresaCreada.js",
        2
      ],
      [
        "src/modules/empresa/domain/events/EmpresaSuspendida.js",
        2
      ],
      [
        "src/modules/human-intervention/domain/events/ConversationLocked.js",
        2
      ],
      [
        "src/modules/human-intervention/domain/events/ConversationClosed.js",
        2
      ],
      [
        "src/modules/human-intervention/domain/events/ConversationCreated.js",
        2
      ],
      [
        "src/modules/human-intervention/application/use-cases/CrearConversationSessionUseCase.js",
        2
      ],
      [
        "src/modules/human-intervention/domain/events/HumanInterventionDetected.js",
        2
      ],
      [
        "src/modules/human-intervention/application/use-cases/DetectarIntervencionHumanaUseCase.js",
        2
      ],
      [
        "src/modules/human-intervention/domain/events/BotResumed.js",
        2
      ],
      [
        "src/modules/human-intervention/application/use-cases/EvaluarReanudacionBotUseCase.js",
        2
      ],
      [
        "src/modules/human-intervention/domain/valueObjects/ConversationState.js",
        2
      ],
      [
        "src/modules/human-intervention/infrastructure/adapters/EvolutionWebhookAdapter.js",
        2
      ],
      [
        "src/modules/human-intervention/domain/repositories/ConversationSessionRepository.js",
        2
      ],
      [
        "src/modules/usuario/domain/events/UsuarioActivado.js",
        2
      ],
      [
        "src/modules/usuario/domain/events/UsuarioActualizado.js",
        2
      ],
      [
        "src/modules/usuario/domain/events/UsuarioCancelado.js",
        2
      ],
      [
        "src/modules/usuario/domain/events/UsuarioCreado.js",
        2
      ],
      [
        "src/modules/usuario/domain/events/UsuarioSuspendido.js",
        2
      ],
      [
        "src/modules/usuario/domain/valueObjects/NombreUsuario.js",
        2
      ],
      [
        "src/modules/usuario/domain/valueObjects/EmailUsuario.js",
        2
      ],
      [
        "src/modules/usuario/domain/valueObjects/RolUsuario.js",
        2
      ],
      [
        "src/modules/usuario/domain/repositories/UsuarioRepository.js",
        2
      ],
      [
        "src/modules/usuario/infrastructure/persistence/PrismaUsuarioRepository.js",
        2
      ],
      [
        "src/modules/whatsapp-sender/domain/entities/OutboundMessage.js",
        2
      ],
      [
        "src/modules/whatsapp-sender/domain/events/MensajeEnviado.js",
        2
      ],
      [
        "src/modules/whatsapp-sender/domain/events/EnvioFallido.js",
        2
      ],
      [
        "src/shared/tenant/TenantError.ts",
        2
      ],
      [
        "src/core/capability/application/ExecuteCapabilityUseCase.js",
        1
      ],
      [
        "src/core/capability/application/ExecuteCapabilityUseCase.test.js",
        1
      ],
      [
        "src/core/capability/application/RegisterCapabilityUseCase.test.js",
        1
      ],
      [
        "src/core/capability/domain/CapabilityRegistry.test.js",
        1
      ],
      [
        "src/core/contracts/ExecutionResult.ts",
        1
      ],
      [
        "src/core/execution-policy/domain/ErrorClassifier.test.js",
        1
      ],
      [
        "src/core/execution-policy/domain/PermissionChecker.test.js",
        1
      ],
      [
        "src/core/execution-policy/domain/RetryPolicy.test.js",
        1
      ],
      [
        "src/core/execution-policy/domain/TimeoutPolicy.test.js",
        1
      ],
      [
        "src/core/kernel/events/EventBus.test.js",
        1
      ],
      [
        "src/core/kernel/events/EventPublisher.test.js",
        1
      ],
      [
        "src/core/security/TenantContext.test.js",
        1
      ],
      [
        "src/core/security/TenantGuard.test.js",
        1
      ],
      [
        "src/e2e/api.e2e.test.js",
        1
      ],
      [
        "src/e2e/database.e2e.test.js",
        1
      ],
      [
        "src/engines/agent-runtime/application/RuntimeEngine.contract.test.js",
        1
      ],
      [
        "src/engines/agent-runtime/application/RuntimeEngine.integration.test.js",
        1
      ],
      [
        "src/engines/agent-runtime/application/RuntimeEngine.test.js",
        1
      ],
      [
        "src/engines/agent-runtime/domain/ExecutionContext.test.js",
        1
      ],
      [
        "src/engines/agent-runtime/domain/ExecutionLifecycle.test.js",
        1
      ],
      [
        "src/engines/agent-runtime/infrastructure/EventDispatcher.test.js",
        1
      ],
      [
        "src/modules/ai/infrastructure/adapters/FakeLLMProvider.js",
        1
      ],
      [
        "src/engines/ai-engine/application/use-cases/GenerarRespuestaUseCase.test.js",
        1
      ],
      [
        "src/engines/ai-engine/domain/valueObjects/AIRequestState.js",
        1
      ],
      [
        "src/engines/conversation-engine/buffer/application/use-cases/AgregarMensajeAlBufferUseCase.js",
        1
      ],
      [
        "src/engines/conversation-engine/buffer/application/use-cases/AgregarMensajeAlBufferUseCase.test.js",
        1
      ],
      [
        "src/engines/conversation-engine/buffer/application/use-cases/ProcesarBufferUseCase.js",
        1
      ],
      [
        "src/engines/conversation-engine/buffer/application/use-cases/CerrarProcesarBufferUseCase.test.js",
        1
      ],
      [
        "src/engines/conversation-engine/buffer/application/workers/BufferExpirationWorker.js",
        1
      ],
      [
        "src/engines/conversation-engine/buffer/application/workers/BufferExpirationWorker.test.js",
        1
      ],
      [
        "src/engines/conversation-engine/buffer/domain/entities/MessageBuffer.test.js",
        1
      ],
      [
        "src/engines/conversation-engine/state-machine/infrastructure/persistence/FakeConversationFlowRepository.js",
        1
      ],
      [
        "src/engines/conversation-engine/state-machine/application/use-cases/IniciarFlujoUseCase.js",
        1
      ],
      [
        "src/engines/conversation-engine/state-machine/application/use-cases/AvanzarEtapaUseCase.js",
        1
      ],
      [
        "src/engines/conversation-engine/state-machine/application/use-cases/FinalizarFlujoUseCase.js",
        1
      ],
      [
        "src/engines/conversation-engine/state-machine/domain/entities/ConversationFlow.test.js",
        1
      ],
      [
        "src/infrastructure/api/contracts/ApiRequest.js",
        1
      ],
      [
        "src/infrastructure/api/middleware/pipeline.js",
        1
      ],
      [
        "src/infrastructure/api/versioning/ApiVersioning.js",
        1
      ],
      [
        "src/infrastructure/api/health/healthController.js",
        1
      ],
      [
        "src/infrastructure/api/openapi/OpenApiController.js",
        1
      ],
      [
        "src/infrastructure/api/infrastructure/ExpressApp.test.js",
        1
      ],
      [
        "src/infrastructure/api/validators/conversationValidators.js",
        1
      ],
      [
        "src/infrastructure/api/mappers/conversationHttpMapper.js",
        1
      ],
      [
        "src/infrastructure/api/interfaces/controllers/ConversationControlController.test.js",
        1
      ],
      [
        "src/infrastructure/api/validators/dashboardValidators.js",
        1
      ],
      [
        "src/infrastructure/api/mappers/dashboardHttpMapper.js",
        1
      ],
      [
        "src/infrastructure/api/interfaces/controllers/DashboardController.test.js",
        1
      ],
      [
        "src/infrastructure/api/mappers/empresaHttpMapper.js",
        1
      ],
      [
        "src/infrastructure/api/validators/empresaValidators.js",
        1
      ],
      [
        "src/infrastructure/api/interfaces/controllers/EmpresaController.test.js",
        1
      ],
      [
        "src/infrastructure/api/mappers/usuarioHttpMapper.js",
        1
      ],
      [
        "src/infrastructure/api/validators/usuarioValidators.js",
        1
      ],
      [
        "src/infrastructure/api/interfaces/controllers/UsuarioController.test.js",
        1
      ],
      [
        "src/infrastructure/api/errors/mapErrorToHttp.js",
        1
      ],
      [
        "src/infrastructure/api/interfaces/middleware/auth.test.js",
        1
      ],
      [
        "src/infrastructure/api/interfaces/middleware/rateLimit.test.js",
        1
      ],
      [
        "src/infrastructure/api/observability/requestContext.js",
        1
      ],
      [
        "src/infrastructure/api/openapi/openApiSpec.js",
        1
      ],
      [
        "src/engines/ai-engine/domain/repositories/LLMProvider.js",
        1
      ],
      [
        "src/infrastructure/api/infrastructure/runApiMock.js",
        1
      ],
      [
        "src/modules/api/infrastructure/ExpressApp.js",
        1
      ],
      [
        "src/modules/dashboard/application/use-cases/UseCases.test.js",
        1
      ],
      [
        "src/modules/dashboard/domain/valueObjects/ValueObjects.test.js",
        1
      ],
      [
        "src/modules/dashboard/domain/repositories/DashboardRepository.js",
        1
      ],
      [
        "src/modules/dashboard/infrastructure/persistence/PrismaDashboardRepository.test.js",
        1
      ],
      [
        "src/modules/empresa/application/use-cases/ActivarEmpresaUseCase.js",
        1
      ],
      [
        "src/modules/empresa/application/use-cases/ActivarEmpresaUseCase.test.js",
        1
      ],
      [
        "src/modules/empresa/application/use-cases/ActualizarEmpresaUseCase.js",
        1
      ],
      [
        "src/modules/empresa/application/use-cases/ActualizarEmpresaUseCase.test.js",
        1
      ],
      [
        "src/modules/empresa/application/use-cases/CancelarEmpresaUseCase.js",
        1
      ],
      [
        "src/modules/empresa/application/use-cases/CancelarEmpresaUseCase.test.js",
        1
      ],
      [
        "src/modules/empresa/application/use-cases/CrearEmpresaUseCase.js",
        1
      ],
      [
        "src/modules/empresa/application/use-cases/CrearEmpresaUseCase.test.js",
        1
      ],
      [
        "src/modules/empresa/application/use-cases/SuspenderEmpresaUseCase.js",
        1
      ],
      [
        "src/modules/empresa/application/use-cases/SuspenderEmpresaUseCase.test.js",
        1
      ],
      [
        "src/modules/empresa/domain/valueObjects/NombreEmpresa.js",
        1
      ],
      [
        "src/modules/empresa/domain/entities/Empresa.test.js",
        1
      ],
      [
        "src/modules/empresa/domain/repositories/EmpresaRepository.test.js",
        1
      ],
      [
        "src/modules/empresa/infrastructure/persistence/FakeEmpresaRepository.js",
        1
      ],
      [
        "src/modules/empresa/infrastructure/persistence/FakeEmpresaRepository.test.js",
        1
      ],
      [
        "src/modules/empresa/infrastructure/persistence/PrismaEmpresaRepository.js",
        1
      ],
      [
        "src/modules/empresa/infrastructure/persistence/PrismaEmpresaRepository.test.js",
        1
      ],
      [
        "src/modules/human-intervention/application/use-cases/BloquearConversacionUseCase.js",
        1
      ],
      [
        "src/modules/human-intervention/application/use-cases/CerrarConversacionUseCase.js",
        1
      ],
      [
        "src/modules/human-intervention/application/use-cases/BloquearCerrarConversacionUseCase.test.js",
        1
      ],
      [
        "src/modules/human-intervention/application/use-cases/CrearConversationSessionUseCase.test.js",
        1
      ],
      [
        "src/modules/human-intervention/application/use-cases/DetectarIntervencionHumanaUseCase.test.js",
        1
      ],
      [
        "src/modules/human-intervention/application/use-cases/EvaluarReanudacionBotUseCase.test.js",
        1
      ],
      [
        "src/modules/human-intervention/application/workers/BotResumptionWorker.js",
        1
      ],
      [
        "src/modules/human-intervention/application/workers/BotResumptionWorker.test.js",
        1
      ],
      [
        "src/modules/human-intervention/domain/entities/ConversationSession.test.js",
        1
      ],
      [
        "src/modules/human-intervention/domain/valueObjects/ConversationState.test.js",
        1
      ],
      [
        "src/modules/human-intervention/infrastructure/adapters/EvolutionWebhookAdapter.test.js",
        1
      ]
    ]
  },
  "wrapperByCategory": {},
  "wrapperSummary": {
    "totalWrappers": 0,
    "pureWrappers": 0,
    "wrappersWithExtraCode": 0,
    "referencedWrappers": 0,
    "unreferencedWrappers": 0
  },
  "tsWrappers": [],
  "jsWrappers": [],
  "jsWrapperDetails": [],
  "jsImports": [
    {
      "from": "src/core/capability/application/ExecuteCapabilityUseCase.test.ts",
      "target": "./ExecuteCapabilityUseCase.test.js",
      "resolved": "src/core/capability/application/ExecuteCapabilityUseCase.test.js",
      "sourceType": "test"
    },
    {
      "from": "src/core/capability/application/RegisterCapabilityUseCase.test.ts",
      "target": "./RegisterCapabilityUseCase.test.js",
      "resolved": "src/core/capability/application/RegisterCapabilityUseCase.test.js",
      "sourceType": "test"
    },
    {
      "from": "src/core/capability/domain/CapabilityRegistry.test.ts",
      "target": "./CapabilityRegistry.test.js",
      "resolved": "src/core/capability/domain/CapabilityRegistry.test.js",
      "sourceType": "test"
    },
    {
      "from": "src/core/execution-policy/domain/ErrorClassifier.test.ts",
      "target": "./ErrorClassifier.test.js",
      "resolved": "src/core/execution-policy/domain/ErrorClassifier.test.js",
      "sourceType": "test"
    },
    {
      "from": "src/core/execution-policy/domain/PermissionChecker.test.ts",
      "target": "./PermissionChecker.test.js",
      "resolved": "src/core/execution-policy/domain/PermissionChecker.test.js",
      "sourceType": "test"
    },
    {
      "from": "src/core/execution-policy/domain/RetryPolicy.test.ts",
      "target": "./RetryPolicy.test.js",
      "resolved": "src/core/execution-policy/domain/RetryPolicy.test.js",
      "sourceType": "test"
    },
    {
      "from": "src/core/execution-policy/domain/TimeoutPolicy.test.ts",
      "target": "./TimeoutPolicy.test.js",
      "resolved": "src/core/execution-policy/domain/TimeoutPolicy.test.js",
      "sourceType": "test"
    },
    {
      "from": "src/core/kernel/events/EventBus.test.ts",
      "target": "./EventBus.test.js",
      "resolved": "src/core/kernel/events/EventBus.test.js",
      "sourceType": "test"
    },
    {
      "from": "src/core/kernel/events/EventPublisher.test.ts",
      "target": "./EventPublisher.test.js",
      "resolved": "src/core/kernel/events/EventPublisher.test.js",
      "sourceType": "test"
    },
    {
      "from": "src/core/security/TenantContext.test.ts",
      "target": "./TenantContext.test.js",
      "resolved": "src/core/security/TenantContext.test.js",
      "sourceType": "test"
    },
    {
      "from": "src/core/security/TenantGuard.test.ts",
      "target": "./TenantGuard.test.js",
      "resolved": "src/core/security/TenantGuard.test.js",
      "sourceType": "test"
    },
    {
      "from": "src/e2e/api.e2e.test.ts",
      "target": "./api.e2e.test.js",
      "resolved": "src/e2e/api.e2e.test.js",
      "sourceType": "test"
    },
    {
      "from": "src/e2e/database.e2e.test.ts",
      "target": "./database.e2e.test.js",
      "resolved": "src/e2e/database.e2e.test.js",
      "sourceType": "test"
    },
    {
      "from": "src/engines/agent-runtime/application/RuntimeEngine.contract.test.ts",
      "target": "./RuntimeEngine.contract.test.js",
      "resolved": "src/engines/agent-runtime/application/RuntimeEngine.contract.test.js",
      "sourceType": "test"
    },
    {
      "from": "src/engines/agent-runtime/application/RuntimeEngine.integration.test.ts",
      "target": "./RuntimeEngine.integration.test.js",
      "resolved": "src/engines/agent-runtime/application/RuntimeEngine.integration.test.js",
      "sourceType": "test"
    },
    {
      "from": "src/engines/agent-runtime/application/RuntimeEngine.test.ts",
      "target": "./RuntimeEngine.test.js",
      "resolved": "src/engines/agent-runtime/application/RuntimeEngine.test.js",
      "sourceType": "test"
    },
    {
      "from": "src/engines/agent-runtime/domain/ExecutionContext.test.ts",
      "target": "./ExecutionContext.test.js",
      "resolved": "src/engines/agent-runtime/domain/ExecutionContext.test.js",
      "sourceType": "test"
    },
    {
      "from": "src/engines/agent-runtime/domain/ExecutionLifecycle.test.ts",
      "target": "./ExecutionLifecycle.test.js",
      "resolved": "src/engines/agent-runtime/domain/ExecutionLifecycle.test.js",
      "sourceType": "test"
    },
    {
      "from": "src/engines/agent-runtime/infrastructure/EventDispatcher.test.ts",
      "target": "./EventDispatcher.test.js",
      "resolved": "src/engines/agent-runtime/infrastructure/EventDispatcher.test.js",
      "sourceType": "test"
    },
    {
      "from": "src/engines/ai-engine/application/use-cases/GenerarRespuestaUseCase.test.ts",
      "target": "./GenerarRespuestaUseCase.test.js",
      "resolved": "src/engines/ai-engine/application/use-cases/GenerarRespuestaUseCase.test.js",
      "sourceType": "test"
    },
    {
      "from": "src/engines/conversation-engine/buffer/application/use-cases/AgregarMensajeAlBufferUseCase.test.ts",
      "target": "./AgregarMensajeAlBufferUseCase.test.js",
      "resolved": "src/engines/conversation-engine/buffer/application/use-cases/AgregarMensajeAlBufferUseCase.test.js",
      "sourceType": "test"
    },
    {
      "from": "src/engines/conversation-engine/buffer/application/use-cases/CerrarProcesarBufferUseCase.test.ts",
      "target": "./CerrarProcesarBufferUseCase.test.js",
      "resolved": "src/engines/conversation-engine/buffer/application/use-cases/CerrarProcesarBufferUseCase.test.js",
      "sourceType": "test"
    },
    {
      "from": "src/engines/conversation-engine/buffer/application/workers/BufferExpirationWorker.test.ts",
      "target": "./BufferExpirationWorker.test.js",
      "resolved": "src/engines/conversation-engine/buffer/application/workers/BufferExpirationWorker.test.js",
      "sourceType": "test"
    },
    {
      "from": "src/engines/conversation-engine/buffer/domain/entities/MessageBuffer.test.ts",
      "target": "./MessageBuffer.test.js",
      "resolved": "src/engines/conversation-engine/buffer/domain/entities/MessageBuffer.test.js",
      "sourceType": "test"
    },
    {
      "from": "src/engines/conversation-engine/state-machine/domain/entities/ConversationFlow.test.ts",
      "target": "./ConversationFlow.test.js",
      "resolved": "src/engines/conversation-engine/state-machine/domain/entities/ConversationFlow.test.js",
      "sourceType": "test"
    },
    {
      "from": "src/infrastructure/api/infrastructure/ExpressApp.test.ts",
      "target": "./ExpressApp.test.js",
      "resolved": "src/infrastructure/api/infrastructure/ExpressApp.test.js",
      "sourceType": "test"
    },
    {
      "from": "src/infrastructure/api/interfaces/controllers/ConversationControlController.test.ts",
      "target": "./ConversationControlController.test.js",
      "resolved": "src/infrastructure/api/interfaces/controllers/ConversationControlController.test.js",
      "sourceType": "test"
    },
    {
      "from": "src/infrastructure/api/interfaces/controllers/DashboardController.test.ts",
      "target": "./DashboardController.test.js",
      "resolved": "src/infrastructure/api/interfaces/controllers/DashboardController.test.js",
      "sourceType": "test"
    },
    {
      "from": "src/infrastructure/api/interfaces/controllers/EmpresaController.test.ts",
      "target": "./EmpresaController.test.js",
      "resolved": "src/infrastructure/api/interfaces/controllers/EmpresaController.test.js",
      "sourceType": "test"
    },
    {
      "from": "src/infrastructure/api/interfaces/controllers/UsuarioController.test.ts",
      "target": "./UsuarioController.test.js",
      "resolved": "src/infrastructure/api/interfaces/controllers/UsuarioController.test.js",
      "sourceType": "test"
    },
    {
      "from": "src/infrastructure/api/interfaces/middleware/auth.test.ts",
      "target": "./auth.test.js",
      "resolved": "src/infrastructure/api/interfaces/middleware/auth.test.js",
      "sourceType": "test"
    },
    {
      "from": "src/infrastructure/api/interfaces/middleware/rateLimit.test.ts",
      "target": "./rateLimit.test.js",
      "resolved": "src/infrastructure/api/interfaces/middleware/rateLimit.test.js",
      "sourceType": "test"
    },
    {
      "from": "src/modules/dashboard/application/use-cases/UseCases.test.ts",
      "target": "./UseCases.test.js",
      "resolved": "src/modules/dashboard/application/use-cases/UseCases.test.js",
      "sourceType": "test"
    },
    {
      "from": "src/modules/dashboard/domain/valueObjects/ValueObjects.test.ts",
      "target": "./ValueObjects.test.js",
      "resolved": "src/modules/dashboard/domain/valueObjects/ValueObjects.test.js",
      "sourceType": "test"
    },
    {
      "from": "src/modules/dashboard/infrastructure/persistence/PrismaDashboardRepository.test.ts",
      "target": "./PrismaDashboardRepository.test.js",
      "resolved": "src/modules/dashboard/infrastructure/persistence/PrismaDashboardRepository.test.js",
      "sourceType": "test"
    },
    {
      "from": "src/modules/empresa/application/use-cases/ActivarEmpresaUseCase.test.ts",
      "target": "./ActivarEmpresaUseCase.test.js",
      "resolved": "src/modules/empresa/application/use-cases/ActivarEmpresaUseCase.test.js",
      "sourceType": "test"
    },
    {
      "from": "src/modules/empresa/application/use-cases/ActualizarEmpresaUseCase.test.ts",
      "target": "./ActualizarEmpresaUseCase.test.js",
      "resolved": "src/modules/empresa/application/use-cases/ActualizarEmpresaUseCase.test.js",
      "sourceType": "test"
    },
    {
      "from": "src/modules/empresa/application/use-cases/CancelarEmpresaUseCase.test.ts",
      "target": "./CancelarEmpresaUseCase.test.js",
      "resolved": "src/modules/empresa/application/use-cases/CancelarEmpresaUseCase.test.js",
      "sourceType": "test"
    },
    {
      "from": "src/modules/empresa/application/use-cases/CrearEmpresaUseCase.test.ts",
      "target": "./CrearEmpresaUseCase.test.js",
      "resolved": "src/modules/empresa/application/use-cases/CrearEmpresaUseCase.test.js",
      "sourceType": "test"
    },
    {
      "from": "src/modules/empresa/application/use-cases/SuspenderEmpresaUseCase.test.ts",
      "target": "./SuspenderEmpresaUseCase.test.js",
      "resolved": "src/modules/empresa/application/use-cases/SuspenderEmpresaUseCase.test.js",
      "sourceType": "test"
    },
    {
      "from": "src/modules/empresa/domain/entities/Empresa.test.ts",
      "target": "./Empresa.test.js",
      "resolved": "src/modules/empresa/domain/entities/Empresa.test.js",
      "sourceType": "test"
    },
    {
      "from": "src/modules/empresa/domain/repositories/EmpresaRepository.test.ts",
      "target": "./EmpresaRepository.test.js",
      "resolved": "src/modules/empresa/domain/repositories/EmpresaRepository.test.js",
      "sourceType": "test"
    },
    {
      "from": "src/modules/empresa/infrastructure/persistence/FakeEmpresaRepository.test.ts",
      "target": "./FakeEmpresaRepository.test.js",
      "resolved": "src/modules/empresa/infrastructure/persistence/FakeEmpresaRepository.test.js",
      "sourceType": "test"
    },
    {
      "from": "src/modules/empresa/infrastructure/persistence/PrismaEmpresaRepository.test.ts",
      "target": "./PrismaEmpresaRepository.test.js",
      "resolved": "src/modules/empresa/infrastructure/persistence/PrismaEmpresaRepository.test.js",
      "sourceType": "test"
    },
    {
      "from": "src/modules/human-intervention/application/use-cases/BloquearCerrarConversacionUseCase.test.ts",
      "target": "./BloquearCerrarConversacionUseCase.test.js",
      "resolved": "src/modules/human-intervention/application/use-cases/BloquearCerrarConversacionUseCase.test.js",
      "sourceType": "test"
    },
    {
      "from": "src/modules/human-intervention/application/use-cases/CrearConversationSessionUseCase.test.ts",
      "target": "./CrearConversationSessionUseCase.test.js",
      "resolved": "src/modules/human-intervention/application/use-cases/CrearConversationSessionUseCase.test.js",
      "sourceType": "test"
    },
    {
      "from": "src/modules/human-intervention/application/use-cases/DetectarIntervencionHumanaUseCase.test.ts",
      "target": "./DetectarIntervencionHumanaUseCase.test.js",
      "resolved": "src/modules/human-intervention/application/use-cases/DetectarIntervencionHumanaUseCase.test.js",
      "sourceType": "test"
    },
    {
      "from": "src/modules/human-intervention/application/use-cases/EvaluarReanudacionBotUseCase.test.ts",
      "target": "./EvaluarReanudacionBotUseCase.test.js",
      "resolved": "src/modules/human-intervention/application/use-cases/EvaluarReanudacionBotUseCase.test.js",
      "sourceType": "test"
    },
    {
      "from": "src/modules/human-intervention/application/workers/BotResumptionWorker.test.ts",
      "target": "./BotResumptionWorker.test.js",
      "resolved": "src/modules/human-intervention/application/workers/BotResumptionWorker.test.js",
      "sourceType": "test"
    },
    {
      "from": "src/modules/human-intervention/domain/entities/ConversationSession.test.ts",
      "target": "./ConversationSession.test.js",
      "resolved": "src/modules/human-intervention/domain/entities/ConversationSession.test.js",
      "sourceType": "test"
    },
    {
      "from": "src/modules/human-intervention/domain/valueObjects/ConversationState.test.ts",
      "target": "./ConversationState.test.js",
      "resolved": "src/modules/human-intervention/domain/valueObjects/ConversationState.test.js",
      "sourceType": "test"
    },
    {
      "from": "src/modules/human-intervention/infrastructure/adapters/EvolutionWebhookAdapter.test.ts",
      "target": "./EvolutionWebhookAdapter.test.js",
      "resolved": "src/modules/human-intervention/infrastructure/adapters/EvolutionWebhookAdapter.test.js",
      "sourceType": "test"
    },
    {
      "from": "src/modules/human-intervention/infrastructure/adapters/EvolutionWebhookHandler.test.ts",
      "target": "./EvolutionWebhookHandler.test.js",
      "resolved": "src/modules/human-intervention/infrastructure/adapters/EvolutionWebhookHandler.test.js",
      "sourceType": "test"
    },
    {
      "from": "src/modules/human-intervention/infrastructure/persistence/FakeConversationSessionRepository.test.ts",
      "target": "./FakeConversationSessionRepository.test.js",
      "resolved": "src/modules/human-intervention/infrastructure/persistence/FakeConversationSessionRepository.test.js",
      "sourceType": "test"
    },
    {
      "from": "src/modules/human-intervention/infrastructure/persistence/PrismaConversationSessionRepository.test.ts",
      "target": "./PrismaConversationSessionRepository.test.js",
      "resolved": "src/modules/human-intervention/infrastructure/persistence/PrismaConversationSessionRepository.test.js",
      "sourceType": "test"
    },
    {
      "from": "src/modules/usuario/application/use-cases/ActivarUsuarioUseCase.test.ts",
      "target": "./ActivarUsuarioUseCase.test.js",
      "resolved": "src/modules/usuario/application/use-cases/ActivarUsuarioUseCase.test.js",
      "sourceType": "test"
    },
    {
      "from": "src/modules/usuario/application/use-cases/ActualizarUsuarioUseCase.test.ts",
      "target": "./ActualizarUsuarioUseCase.test.js",
      "resolved": "src/modules/usuario/application/use-cases/ActualizarUsuarioUseCase.test.js",
      "sourceType": "test"
    },
    {
      "from": "src/modules/usuario/application/use-cases/CancelarUsuarioUseCase.test.ts",
      "target": "./CancelarUsuarioUseCase.test.js",
      "resolved": "src/modules/usuario/application/use-cases/CancelarUsuarioUseCase.test.js",
      "sourceType": "test"
    },
    {
      "from": "src/modules/usuario/application/use-cases/CrearUsuarioUseCase.test.ts",
      "target": "./CrearUsuarioUseCase.test.js",
      "resolved": "src/modules/usuario/application/use-cases/CrearUsuarioUseCase.test.js",
      "sourceType": "test"
    },
    {
      "from": "src/modules/usuario/application/use-cases/SuspenderUsuarioUseCase.test.ts",
      "target": "./SuspenderUsuarioUseCase.test.js",
      "resolved": "src/modules/usuario/application/use-cases/SuspenderUsuarioUseCase.test.js",
      "sourceType": "test"
    },
    {
      "from": "src/modules/usuario/domain/entities/Usuario.test.ts",
      "target": "./Usuario.test.js",
      "resolved": "src/modules/usuario/domain/entities/Usuario.test.js",
      "sourceType": "test"
    },
    {
      "from": "src/modules/usuario/infrastructure/persistence/FakeUsuarioRepository.test.ts",
      "target": "./FakeUsuarioRepository.test.js",
      "resolved": "src/modules/usuario/infrastructure/persistence/FakeUsuarioRepository.test.js",
      "sourceType": "test"
    },
    {
      "from": "src/modules/usuario/infrastructure/persistence/PrismaUsuarioRepository.integration.test.ts",
      "target": "./PrismaUsuarioRepository.integration.test.js",
      "resolved": "src/modules/usuario/infrastructure/persistence/PrismaUsuarioRepository.integration.test.js",
      "sourceType": "test"
    },
    {
      "from": "src/modules/usuario/infrastructure/persistence/PrismaUsuarioRepository.test.ts",
      "target": "./PrismaUsuarioRepository.test.js",
      "resolved": "src/modules/usuario/infrastructure/persistence/PrismaUsuarioRepository.test.js",
      "sourceType": "test"
    },
    {
      "from": "src/modules/whatsapp-sender/application/use-cases/EnviarMensajeUseCase.test.ts",
      "target": "./EnviarMensajeUseCase.test.js",
      "resolved": "src/modules/whatsapp-sender/application/use-cases/EnviarMensajeUseCase.test.js",
      "sourceType": "test"
    },
    {
      "from": "src/shared/config/env.test.ts",
      "target": "./env.test.js",
      "resolved": "src/shared/config/env.test.js",
      "sourceType": "test"
    },
    {
      "from": "src/shared/database/prisma.test.ts",
      "target": "./prisma.test.js",
      "resolved": "src/shared/database/prisma.test.js",
      "sourceType": "test"
    },
    {
      "from": "src/shared/errors/DomainError.test.ts",
      "target": "./DomainError.test.js",
      "resolved": "src/shared/errors/DomainError.test.js",
      "sourceType": "test"
    },
    {
      "from": "src/shared/errors/NotFoundError.test.ts",
      "target": "./NotFoundError.test.js",
      "resolved": "src/shared/errors/NotFoundError.test.js",
      "sourceType": "test"
    },
    {
      "from": "src/shared/errors/ValidationError.test.ts",
      "target": "./ValidationError.test.js",
      "resolved": "src/shared/errors/ValidationError.test.js",
      "sourceType": "test"
    },
    {
      "from": "src/shared/events/EventSubscriber.test.ts",
      "target": "./EventSubscriber.test.js",
      "resolved": "src/shared/events/EventSubscriber.test.js",
      "sourceType": "test"
    },
    {
      "from": "src/shared/logger/logger.test.ts",
      "target": "./logger.test.js",
      "resolved": "src/shared/logger/logger.test.js",
      "sourceType": "test"
    },
    {
      "from": "src/shared/uuid/UuidGenerator.test.ts",
      "target": "./UuidGenerator.test.js",
      "resolved": "src/shared/uuid/UuidGenerator.test.js",
      "sourceType": "test"
    }
  ]
}